astroeasy/__init__.py
astroeasy/cli.py
astroeasy/config.py
astroeasy/constants.py
astroeasy/indices.py
astroeasy/models.py
astroeasy/runner.py
astroeasy/dotnet/Dockerfile
astroeasy/dotnet/__init__.py
astroeasy/dotnet/docker.py
astroeasy/dotnet/local.py
astroeasy/dotnet/runner.py
astroeasy-0.2.0.dist-info/METADATA
astroeasy-0.2.0.dist-info/WHEEL
astroeasy-0.2.0.dist-info/entry_points.txt
astroeasy-0.2.0.dist-info/licenses/LICENSE
astroeasy-0.2.0.dist-info/RECORD
