Metadata-Version: 2.4
Name: astroeasy
Version: 0.2.0
Summary: Astrometry.net made easy - plate solving and index management
Project-URL: Homepage, https://github.com/zgazak/astroeasy
Project-URL: Issues, https://github.com/zgazak/astroeasy/issues
Project-URL: Documentation, https://github.com/zgazak/astroeasy#readme
Author-email: Zach <jzg@alum.mit.edu>
License-Expression: MIT
License-File: LICENSE
Keywords: astrometry,astronomy,plate-solving,wcs
Classifier: Development Status :: 4 - Beta
Classifier: Intended Audience :: Science/Research
Classifier: License :: OSI Approved :: MIT License
Classifier: Operating System :: OS Independent
Classifier: Programming Language :: Python :: 3
Classifier: Programming Language :: Python :: 3.11
Classifier: Programming Language :: Python :: 3.12
Classifier: Topic :: Scientific/Engineering :: Astronomy
Requires-Python: >=3.11
Requires-Dist: astropy>=5.0
Requires-Dist: numpy>=1.20
Requires-Dist: pyyaml>=6.0
Requires-Dist: tqdm>=4.0
Provides-Extra: dev
Requires-Dist: build>=1.4.0; extra == 'dev'
Requires-Dist: genbadge[coverage,tests]>=1.1.3; extra == 'dev'
Requires-Dist: pytest-cov>=4.0; extra == 'dev'
Requires-Dist: pytest>=7.0; extra == 'dev'
Requires-Dist: ruff>=0.4.0; extra == 'dev'
Requires-Dist: twine>=6.2.0; extra == 'dev'
